setup.py
pepnet/__init__.py
pepnet/amino_acids.py
pepnet/encoder.py
pepnet/losses.py
pepnet/nn_helpers.py
pepnet/numeric.py
pepnet/numeric_input.py
pepnet/output.py
pepnet/predictor.py
pepnet/sequence_helpers.py
pepnet/sequence_input.py
pepnet.egg-info/PKG-INFO
pepnet.egg-info/SOURCES.txt
pepnet.egg-info/dependency_links.txt
pepnet.egg-info/pbr.json
pepnet.egg-info/requires.txt
pepnet.egg-info/top_level.txt
pepnet/keras_layers/__init__.py
pepnet/keras_layers/drop_mask.py
pepnet/keras_layers/masked_conv1d.py
pepnet/keras_layers/masked_global_average_pooling.py
pepnet/keras_layers/masked_global_max_pooling.py
pepnet/keras_layers/masked_maxpooling1d.py
pepnet/keras_layers/masked_slice.py
pepnet/synthetic_data/__init__.py
pepnet/synthetic_data/random_peptides.py
pepnet/synthetic_data/subsequence.py
test/test_amino_acids.py
test/test_conv.py
test/test_encoder.py
test/test_feedforward.py
test/test_highway_network_helper.py
test/test_predictor.py
test/test_predictor_serialization.py
test/test_rnn.py
test/test_sequence_context.py