Metadata-Version: 1.1
Name: pepnet
Version: 0.3.2
Summary: Neural networks for amino acid sequences
Home-page: https://github.com/hammerlab/pepnet
Author: Alex Rubinsteyn
Author-email: alex.rubinsteyn@mssm.edu
License: http://www.apache.org/licenses/LICENSE-2.0.html
Platform: UNKNOWN
Classifier: Development Status :: 3 - Alpha
Classifier: Environment :: Console
Classifier: Operating System :: OS Independent
Classifier: Intended Audience :: Science/Research
Classifier: License :: OSI Approved :: Apache Software License
Classifier: Programming Language :: Python
Classifier: Topic :: Scientific/Engineering :: Bio-Informatics
